MANIFEST.in
README.rst
setup.py
allein_zu_haus/__init__.py
allein_zu_haus/_aligner_test.py
allein_zu_haus/_callein_zu_haus.cpp
allein_zu_haus/_callein_zu_haus.pyx
allein_zu_haus/align.cpp
allein_zu_haus/align.hpp
allein_zu_haus.egg-info/PKG-INFO
allein_zu_haus.egg-info/SOURCES.txt
allein_zu_haus.egg-info/dependency_links.txt
allein_zu_haus.egg-info/not-zip-safe
allein_zu_haus.egg-info/top_level.txt