Metadata-Version: 1.1
Name: allein_zu_haus
Version: 0.1.3
Summary: Needleman-Wunsch quality-aware sequence alignmenti, primarily for use with a full aligner like GEM.
Home-page: UNKNOWN
Author: Tali Raveh-Sadka, Ami Tavory, and Shahar Azulay
Author-email: atavory@gmail.com
License: License :: OSI Approved :: BSD License
Platform: UNKNOWN
Classifier: Development Status :: 4 - Beta
Classifier: Intended Audience :: Science/Research
Classifier: License :: OSI Approved :: BSD License
Classifier: Operating System :: OS Independent
Classifier: Programming Language :: Python
Classifier: Programming Language :: Python :: 2.7
Classifier: Programming Language :: Python :: 3
Classifier: Programming Language :: C++
Classifier: Topic :: Scientific/Engineering
Classifier: Topic :: Scientific/Engineering :: Bio-Informatics
Requires: numpy
Requires: cython
